ProgrammingLanguagesLectureNotesNeuCs4400/README.md
ProgrammingLanguagesLectureNotesNeuCs4400/__init__.py
ProgrammingLanguagesLectureNotesNeuCs4400/__main__.py
ProgrammingLanguagesLectureNotesNeuCs4400/file.epub
ProgrammingLanguagesLectureNotesNeuCs4400/index.html
ProgrammingLanguagesLectureNotesNeuCs4400/css/__init__.py
ProgrammingLanguagesLectureNotesNeuCs4400/css/annotations.css
ProgrammingLanguagesLectureNotesNeuCs4400/css/main.css
ProgrammingLanguagesLectureNotesNeuCs4400/css/normalize.css
ProgrammingLanguagesLectureNotesNeuCs4400/css/popup.css
ProgrammingLanguagesLectureNotesNeuCs4400/font/__init__.py
ProgrammingLanguagesLectureNotesNeuCs4400/font/fontello.eot
ProgrammingLanguagesLectureNotesNeuCs4400/font/fontello.svg
ProgrammingLanguagesLectureNotesNeuCs4400/font/fontello.ttf
ProgrammingLanguagesLectureNotesNeuCs4400/font/fontello.woff
ProgrammingLanguagesLectureNotesNeuCs4400/img/__init__.py
ProgrammingLanguagesLectureNotesNeuCs4400/img/annotator-glyph-sprite.png
ProgrammingLanguagesLectureNotesNeuCs4400/img/annotator-icon-sprite.png
ProgrammingLanguagesLectureNotesNeuCs4400/img/apple-touch-icon.png
ProgrammingLanguagesLectureNotesNeuCs4400/img/cancelfullscreen.png
ProgrammingLanguagesLectureNotesNeuCs4400/img/close.png
ProgrammingLanguagesLectureNotesNeuCs4400/img/fullscreen.png
ProgrammingLanguagesLectureNotesNeuCs4400/img/loader.gif
ProgrammingLanguagesLectureNotesNeuCs4400/img/menu-icon.png
ProgrammingLanguagesLectureNotesNeuCs4400/img/save.png
ProgrammingLanguagesLectureNotesNeuCs4400/img/saved.png
ProgrammingLanguagesLectureNotesNeuCs4400/img/settings-s.png
ProgrammingLanguagesLectureNotesNeuCs4400/img/settings.png
ProgrammingLanguagesLectureNotesNeuCs4400/img/star.png
ProgrammingLanguagesLectureNotesNeuCs4400/js/__init__.py
ProgrammingLanguagesLectureNotesNeuCs4400/js/epub.js
ProgrammingLanguagesLectureNotesNeuCs4400/js/epub.min.js
ProgrammingLanguagesLectureNotesNeuCs4400/js/epub.min.map
ProgrammingLanguagesLectureNotesNeuCs4400/js/hooks.min.js
programming_languages_lecture_notes_neu_cs4400-2024.3.2.0.dist-info/METADATA
programming_languages_lecture_notes_neu_cs4400-2024.3.2.0.dist-info/WHEEL
programming_languages_lecture_notes_neu_cs4400-2024.3.2.0.dist-info/entry_points.txt
programming_languages_lecture_notes_neu_cs4400-2024.3.2.0.dist-info/top_level.txt
programming_languages_lecture_notes_neu_cs4400-2024.3.2.0.dist-info/RECORD
